pacman_game/__init__.py
pacman_game/exceptions.py
pacman_game/game.py
pacman_game/gamemaze.py
pacman_game/ghost.py
pacman_game/main.py
pacman_game/pacman.py
pacman_game/person.py
pacman_game/utils.py
pacman_game-1.0.3.dev1.dist-info/DESCRIPTION.rst
pacman_game-1.0.3.dev1.dist-info/METADATA
pacman_game-1.0.3.dev1.dist-info/RECORD
pacman_game-1.0.3.dev1.dist-info/WHEEL
pacman_game-1.0.3.dev1.dist-info/entry_points.txt
pacman_game-1.0.3.dev1.dist-info/metadata.json
pacman_game-1.0.3.dev1.dist-info/top_level.txt
