Metadata-Version: 2.0
Name: pacman-game
Version: 1.0.3.dev1
Summary: A Pacman Like Game with new and interesting new features.
Home-page: https://github.com/ParthKolekar/pacman-game
Author: Parth Kolekar
Author-email: parth.kolekar@students.iiit.ac.in
License: BSD
Download-URL: https://github.com/ParthKolekar/pacman-game/tarball/1.0.3.dev1
Keywords: pacman console ai game
Platform: UNKNOWN
Classifier: Development Status :: 3 - Alpha
Classifier: Intended Audience :: Developers
Classifier: Programming Language :: Python :: 2
